{"title":"Combined feed","url":"https://MusicReleaseKR.github.io/genie/all.xml","elements":[{"title":"scabiosa (지니 모바일 ─ 최신음악)","contents":"migoo","link":"http://mw.genie.co.kr/detail/albumInfo?axnm=84884891","retrieved":1710990925093,"image":"https://image.genie.co.kr/Y/IMAGE/IMG_ALBUM/084/884/891/84884891_1710488704958_1_200x200.JPG"},{"title":"DIGITAL WORLD (지니 모바일 ─ 최신음악)","contents":"Austn (오스틴)","link":"http://mw.genie.co.kr/detail/albumInfo?axnm=84894947","retrieved":1710990925096,"image":"https://image.genie.co.kr/Y/IMAGE/IMG_ALBUM/084/894/947/84894947_1710927800384_1_200x200.JPG"},{"title":"춘향 (지니 모바일 ─ 최신음악)","contents":"고영열","link":"http://mw.genie.co.kr/detail/albumInfo?axnm=84902003","retrieved":1710990925097,"image":"https://image.genie.co.kr/Y/IMAGE/IMG_ALBUM/084/902/003/84902003_1710985579209_1_200x200.JPG"},{"title":"cts8 (지니 모바일 ─ 최신음악)","contents":"KIRARA (키라라)","link":"http://mw.genie.co.kr/detail/albumInfo?axnm=84887499","retrieved":1710990925103,"image":"https://image.genie.co.kr/Y/IMAGE/IMG_ALBUM/084/887/499/84887499_1710924420044_1_200x200.JPG"},{"title":"우리는 (지니 모바일 ─ 최신음악)","contents":"구본암","link":"http://mw.genie.co.kr/detail/albumInfo?axnm=84903017","retrieved":1710990925104,"image":"https://image.genie.co.kr/Y/IMAGE/IMG_ALBUM/084/903/017/84903017_1710930233608_1_200x200.JPG"},{"title":"Tunnel (지니 모바일 ─ 최신음악)","contents":"ecru (에크루)","link":"http://mw.genie.co.kr/detail/albumInfo?axnm=84896743","retrieved":1710990925106,"image":"https://image.genie.co.kr/Y/IMAGE/IMG_ALBUM/084/896/743/84896743_1710809503717_1_200x200.JPG"},{"title":"유명가수와 길거리 심사단 EP.3 (지니 모바일 ─ 최신음악)","contents":"Various Artists","link":"http://mw.genie.co.kr/detail/albumInfo?axnm=84902058","retrieved":1710990925116,"image":"https://image.genie.co.kr/Y/IMAGE/IMG_ALBUM/084/902/058/84902058_1710930238676_1_200x200.JPG"},{"title":"Deserve (지니 모바일 ─ 최신음악)","contents":"OSSH","link":"http://mw.genie.co.kr/detail/albumInfo?axnm=84880531","retrieved":1710990925116,"image":"https://image.genie.co.kr/Y/IMAGE/IMG_ALBUM/084/880/531/84880531_1710488690999_1_200x200.JPG"},{"title":"피도 눈물도 없이 OST Part.9 (지니 모바일 ─ 최신음악)","contents":"제이세라 (J-Cera)","link":"http://mw.genie.co.kr/detail/albumInfo?axnm=84887926","retrieved":1710990925117,"image":"https://image.genie.co.kr/Y/IMAGE/IMG_ALBUM/084/887/926/84887926_1710481892222_1_200x200.JPG"},{"title":"로드 오브 히어로즈 OST Part 5 (지니 모바일 ─ 최신음악)","contents":"마치 (MRCH) &amp; LYN (CV. Yoshino Nanjo)","link":"http://mw.genie.co.kr/detail/albumInfo?axnm=84894049","retrieved":1710990925117,"image":"https://image.genie.co.kr/Y/IMAGE/IMG_ALBUM/084/894/049/84894049_1710916332061_1_200x200.JPG"},{"title":"Month Lee 2403 (지니 모바일 ─ 최신음악)","contents":"이세준 (유리상자)","link":"http://mw.genie.co.kr/detail/albumInfo?axnm=84888104","retrieved":1710990925117,"image":"https://image.genie.co.kr/Y/IMAGE/IMG_ALBUM/084/888/104/84888104_1710496983656_1_200x200.JPG"},{"title":"벚꽃, 개나리 그리고 배신자들 (지니 모바일 ─ 최신음악)","contents":"웃웃 (utut)","link":"http://mw.genie.co.kr/detail/albumInfo?axnm=84902302","retrieved":1710990925117,"image":"https://image.genie.co.kr/Y/IMAGE/IMG_ALBUM/084/902/302/84902302_1710926818970_1_200x200.JPG"},{"title":"너는 잘 지내 보여 (지니 모바일 ─ 최신음악)","contents":"란 (Ran)","link":"http://mw.genie.co.kr/detail/albumInfo?axnm=84887943","retrieved":1710990925117,"image":"https://image.genie.co.kr/Y/IMAGE/IMG_ALBUM/084/887/943/84887943_1710930190815_1_200x200.JPG"},{"title":"행복을 담았어 (지니 모바일 ─ 최신음악)","contents":"세진 (Sejin)","link":"http://mw.genie.co.kr/detail/albumInfo?axnm=84893788","retrieved":1710990925117,"image":"https://image.genie.co.kr/Y/IMAGE/IMG_ALBUM/084/893/788/84893788_1710918831689_1_200x200.JPG"},{"title":"던전앤파이터 모바일 : Crack Is Over (Original Game Soundtrack) (지니 모바일 ─ 최신음악)","contents":"정영걸 (NEOPLE)","link":"http://mw.genie.co.kr/detail/albumInfo?axnm=84887970","retrieved":1710990925120,"image":"https://image.genie.co.kr/Y/IMAGE/IMG_ALBUM/084/887/970/84887970_1710484890980_1_200x200.JPG"},{"title":"BOAT (지니 모바일 ─ 최신음악)","contents":"LAKTA","link":"http://mw.genie.co.kr/detail/albumInfo?axnm=84899326","retrieved":1710990925121,"image":"https://image.genie.co.kr/Y/IMAGE/IMG_ALBUM/084/899/326/84899326_1710930193884_1_200x200.JPG"},{"title":"만년사랑 (지니 모바일 ─ 최신음악)","contents":"오강혁","link":"http://mw.genie.co.kr/detail/albumInfo?axnm=84902174","retrieved":1710990925124,"image":"https://image.genie.co.kr/Y/IMAGE/IMG_ALBUM/084/902/174/84902174_1710982953743_1_200x200.JPG"},{"title":"Spirit (지니 모바일 ─ 최신음악)","contents":"Chloe snow","link":"http://mw.genie.co.kr/detail/albumInfo?axnm=84887869","retrieved":1710990925127,"image":"https://image.genie.co.kr/Y/IMAGE/IMG_ALBUM/084/887/869/84887869_1710487686101_1_200x200.JPG"},{"title":"Stay (지니 모바일 ─ 최신음악)","contents":"히튼 (Hitten)","link":"http://mw.genie.co.kr/detail/albumInfo?axnm=84897746","retrieved":1710990925136,"image":"https://image.genie.co.kr/Y/IMAGE/IMG_ALBUM/084/897/746/84897746_1710930199820_1_200x200.JPG"},{"title":"끝내주는 해결사 OST (지니 모바일 ─ 최신음악)","contents":"Various Artists","link":"http://mw.genie.co.kr/detail/albumInfo?axnm=84903003","retrieved":1710990925136,"image":"https://image.genie.co.kr/Y/IMAGE/IMG_ALBUM/084/903/003/84903003_1710930242189_1_200x200.JPG"}]}