{"title":"Combined feed","url":"https://MusicReleaseKR.github.io/genie/all.xml","elements":[{"title":"미치지 않고서 어떻게 널 잊어 (지니 모바일 ─ 최신음악)","contents":"포맨 (4MEN)","link":"http://mw.genie.co.kr/detail/albumInfo?axnm=85245576","retrieved":1717924535429,"image":"https://image.genie.co.kr/Y/IMAGE/IMG_ALBUM/085/245/576/85245576_1717117704666_1_200x200.JPG"},{"title":"졸업 OST Part 4 (지니 모바일 ─ 최신음악)","contents":"The Restless Age","link":"http://mw.genie.co.kr/detail/albumInfo?axnm=85270267","retrieved":1717924535429,"image":"https://image.genie.co.kr/Y/IMAGE/IMG_ALBUM/085/270/267/85270267_1717576669817_1_200x200.JPG"},{"title":"인피니트 (INFINITE) Digital Single ［Flower］ (지니 모바일 ─ 최신음악)","contents":"인피니트 (Infinite)","link":"http://mw.genie.co.kr/detail/albumInfo?axnm=85280440","retrieved":1717924535429,"image":"https://image.genie.co.kr/Y/IMAGE/IMG_ALBUM/085/280/440/85280440_1717728720059_1_200x200.JPG"},{"title":"연애의 참견 2024 OST Part.14 (지니 모바일 ─ 최신음악)","contents":"이보람","link":"http://mw.genie.co.kr/detail/albumInfo?axnm=85271301","retrieved":1717924535430,"image":"https://image.genie.co.kr/Y/IMAGE/IMG_ALBUM/085/271/301/85271301_1717574535670_1_200x200.JPG"},{"title":"엄마, 단둘이 여행 갈래? OST - 헨 (지니 모바일 ─ 최신음악)","contents":"헨 (HEN)","link":"http://mw.genie.co.kr/detail/albumInfo?axnm=85266061","retrieved":1717924535430,"image":"https://image.genie.co.kr/Y/IMAGE/IMG_ALBUM/085/266/061/85266061_1717573246128_1_200x200.JPG"},{"title":"사자는 치즈가 된 거야 (The lion that became cheese) (지니 모바일 ─ 최신음악)","contents":"유라 (youra) &amp; 만동 (Mandong)","link":"http://mw.genie.co.kr/detail/albumInfo?axnm=85265588","retrieved":1717924535436,"image":"https://image.genie.co.kr/Y/IMAGE/IMG_ALBUM/085/265/588/85265588_1717571036604_1_200x200.JPG"},{"title":"예보에 없는 (지니 모바일 ─ 최신음악)","contents":"KCM","link":"http://mw.genie.co.kr/detail/albumInfo?axnm=85280420","retrieved":1717924535436,"image":"https://image.genie.co.kr/Y/IMAGE/IMG_ALBUM/085/280/420/85280420_1717728688935_1_200x200.JPG"},{"title":"Offline (지니 모바일 ─ 최신음악)","contents":"로렐 (LauRel)","link":"http://mw.genie.co.kr/detail/albumInfo?axnm=85265672","retrieved":1717924535438,"image":"https://image.genie.co.kr/Y/IMAGE/IMG_ALBUM/085/265/672/85265672_1717576327112_1_200x200.JPG"},{"title":"Die For Her (지니 모바일 ─ 최신음악)","contents":"PYMEL (파이멜)","link":"http://mw.genie.co.kr/detail/albumInfo?axnm=85265776","retrieved":1717924535438,"image":"https://image.genie.co.kr/Y/IMAGE/IMG_ALBUM/085/265/776/85265776_1717482702225_1_200x200.JPG"},{"title":"히어로는 아닙니다만 OST (지니 모바일 ─ 최신음악)","contents":"Various Artists","link":"http://mw.genie.co.kr/detail/albumInfo?axnm=85271251","retrieved":1717924535439,"image":"https://image.genie.co.kr/Y/IMAGE/IMG_ALBUM/085/271/251/85271251_1717577217199_1_200x200.JPG"},{"title":"이럴거면 왜 (지니 모바일 ─ 최신음악)","contents":"Western P.I.G","link":"http://mw.genie.co.kr/detail/albumInfo?axnm=85271071","retrieved":1717902992439,"image":"https://image.genie.co.kr/Y/IMAGE/IMG_ALBUM/085/271/071/85271071_1717571027093_1_200x200.JPG"},{"title":"natural (지니 모바일 ─ 최신음악)","contents":"이츠","link":"http://mw.genie.co.kr/detail/albumInfo?axnm=85265850","retrieved":1717902992441,"image":"https://image.genie.co.kr/Y/IMAGE/IMG_ALBUM/085/265/850/85265850_1717986116459_1_200x200.JPG"},{"title":"'hello i'm lofi' vol.3 (지니 모바일 ─ 최신음악)","contents":"lofi","link":"http://mw.genie.co.kr/detail/albumInfo?axnm=85270441","retrieved":1717902992444,"image":"https://image.genie.co.kr/Y/IMAGE/IMG_ALBUM/085/270/441/85270441_1717553838307_1_200x200.JPG"},{"title":"Better World (지니 모바일 ─ 최신음악)","contents":"헤이즈 문 (Haze Moon)","link":"http://mw.genie.co.kr/detail/albumInfo?axnm=85261255","retrieved":1717902992445,"image":"https://image.genie.co.kr/Y/IMAGE/IMG_ALBUM/085/261/255/85261255_1717464100149_1_200x200.JPG"},{"title":"우리 사이에 (지니 모바일 ─ 최신음악)","contents":"Osshun Gum","link":"http://mw.genie.co.kr/detail/albumInfo?axnm=85270448","retrieved":1717902992455,"image":"https://image.genie.co.kr/Y/IMAGE/IMG_ALBUM/085/270/448/85270448_1717563541708_1_200x200.JPG"},{"title":"지혜 (지니 모바일 ─ 최신음악)","contents":"SOI (소이)","link":"http://mw.genie.co.kr/detail/albumInfo?axnm=85265851","retrieved":1717902992455,"image":"https://image.genie.co.kr/Y/IMAGE/IMG_ALBUM/085/265/851/85265851_1717484490054_1_200x200.JPG"},{"title":"hey1996 로맨스 No.3 (지니 모바일 ─ 최신음악)","contents":"hey1996","link":"http://mw.genie.co.kr/detail/albumInfo?axnm=85271047","retrieved":1717902992455,"image":"https://image.genie.co.kr/Y/IMAGE/IMG_ALBUM/085/271/047/85271047_1717574509775_1_200x200.JPG"},{"title":"Set Me Free (지니 모바일 ─ 최신음악)","contents":"Sunnie (써니)","link":"http://mw.genie.co.kr/detail/albumInfo?axnm=85271205","retrieved":1717902992455,"image":"https://image.genie.co.kr/Y/IMAGE/IMG_ALBUM/085/271/205/85271205_1717577081465_1_200x200.JPG"},{"title":"시한부 (지니 모바일 ─ 최신음악)","contents":"MODI (김용진)","link":"http://mw.genie.co.kr/detail/albumInfo?axnm=85271340","retrieved":1717902992456,"image":"https://image.genie.co.kr/Y/IMAGE/IMG_ALBUM/085/271/340/85271340_1717571200433_1_200x200.JPG"},{"title":"카운트다운! (지니 모바일 ─ 최신음악)","contents":"환상문학청년","link":"http://mw.genie.co.kr/detail/albumInfo?axnm=85264939","retrieved":1717902992456,"image":"https://image.genie.co.kr/Y/IMAGE/IMG_ALBUM/085/264/939/85264939_1717564061628_1_200x200.JPG"}]}