{"title":"Combined feed","url":"https://MusicReleaseKR.github.io/genie/all.xml","elements":[{"title":"끝없이 (지니 모바일 ─ 최신음악)","contents":"JIN (러블리즈)","link":"http://mw.genie.co.kr/detail/albumInfo?axnm=83401491","retrieved":1673061338716,"image":"http://image.genie.co.kr/Y/IMAGE/IMG_ALBUM/083/401/491/83401491_1672990356252_1_200x200.JPG"},{"title":"봄눈 (지니 모바일 ─ 최신음악)","contents":"디에고 (diego)","link":"http://mw.genie.co.kr/detail/albumInfo?axnm=83390247","retrieved":1673061338716,"image":"http://image.genie.co.kr/Y/IMAGE/IMG_ALBUM/083/390/247/83390247_1672711411381_1_200x200.JPG"},{"title":"내게 말해봐요 (지니 모바일 ─ 최신음악)","contents":"제주청년","link":"http://mw.genie.co.kr/detail/albumInfo?axnm=83404152","retrieved":1673061338716,"image":"http://image.genie.co.kr/Y/IMAGE/IMG_ALBUM/083/404/152/83404152_1672994358032_1_200x200.JPG"},{"title":"퍼스널 노래 (지니 모바일 ─ 최신음악)","contents":"그네","link":"http://mw.genie.co.kr/detail/albumInfo?axnm=83401024","retrieved":1673061338717,"image":"http://image.genie.co.kr/Y/IMAGE/IMG_ALBUM/083/401/024/83401024_1672986350296_1_200x200.JPG"},{"title":"쇼미더머니 11 (Inst.) (지니 모바일 ─ 최신음악)","contents":"Various Artists","link":"http://mw.genie.co.kr/detail/albumInfo?axnm=83397216","retrieved":1673061338717,"image":"http://image.genie.co.kr/Y/IMAGE/IMG_ALBUM/083/397/216/83397216_1672987364485_1_200x200.JPG"},{"title":"Youth (지니 모바일 ─ 최신음악)","contents":"HERD","link":"http://mw.genie.co.kr/detail/albumInfo?axnm=83403243","retrieved":1673061338717,"image":"http://image.genie.co.kr/Y/IMAGE/IMG_ALBUM/083/403/243/83403243_1672991722963_1_200x200.JPG"},{"title":"지구의 너, 우주의 나 (지니 모바일 ─ 최신음악)","contents":"심각한 개구리 &amp; 원태림","link":"http://mw.genie.co.kr/detail/albumInfo?axnm=83400863","retrieved":1673061338717,"image":"http://image.genie.co.kr/Y/IMAGE/IMG_ALBUM/083/400/863/83400863_1672986414384_1_200x200.JPG"},{"title":"시네마천국 (Cinema Paradiso) (지니 모바일 ─ 최신음악)","contents":"강동훈","link":"http://mw.genie.co.kr/detail/albumInfo?axnm=83403320","retrieved":1673061338725,"image":"http://image.genie.co.kr/Y/IMAGE/IMG_ALBUM/083/403/320/83403320_1672986539067_1_200x200.JPG"},{"title":"커피여우 김삼월 OST Part.19 (지니 모바일 ─ 최신음악)","contents":"주원탁 (JUWONTAK)","link":"http://mw.genie.co.kr/detail/albumInfo?axnm=83393291","retrieved":1673061338725,"image":"http://image.genie.co.kr/Y/IMAGE/IMG_ALBUM/083/393/291/83393291_1672908653016_1_200x200.JPG"},{"title":"Gold (지니 모바일 ─ 최신음악)","contents":"Kass","link":"http://mw.genie.co.kr/detail/albumInfo?axnm=83397692","retrieved":1673061338726,"image":"http://image.genie.co.kr/Y/IMAGE/IMG_ALBUM/083/397/692/83397692_1672823917472_1_200x200.JPG"},{"title":"In My Dream (지니 모바일 ─ 최신음악)","contents":"줄리 (Julie Joohee Jeon)","link":"http://mw.genie.co.kr/detail/albumInfo?axnm=83404247","retrieved":1673061338728,"image":"http://image.genie.co.kr/Y/IMAGE/IMG_ALBUM/083/404/247/83404247_1672989338804_1_200x200.JPG"},{"title":"국가가 부른다 Part40 (지니 모바일 ─ 최신음악)","contents":"Various Artists","link":"http://mw.genie.co.kr/detail/albumInfo?axnm=83401451","retrieved":1673061338731,"image":"http://image.genie.co.kr/Y/IMAGE/IMG_ALBUM/083/401/451/83401451_1672991662872_1_200x200.JPG"},{"title":"술꾼도시여자들2 OST Part 5 (지니 모바일 ─ 최신음악)","contents":"조유리","link":"http://mw.genie.co.kr/detail/albumInfo?axnm=83390799","retrieved":1672996457774,"image":"http://image.genie.co.kr/Y/IMAGE/IMG_ALBUM/083/390/799/83390799_1672983591795_1_200x200.JPG"},{"title":"비싼 숙취 (지니 모바일 ─ 최신음악)","contents":"이승윤","link":"http://mw.genie.co.kr/detail/albumInfo?axnm=83400985","retrieved":1672996457777,"image":"http://image.genie.co.kr/Y/IMAGE/IMG_ALBUM/083/400/985/83400985_1672966238536_1_200x200.JPG"},{"title":"딩고와 키카코 하우스 두번째 (지니 모바일 ─ 최신음악)","contents":"PATEKO (파테코) &amp; Jayci yucca (제이씨 유카) &amp; Kid Wine","link":"http://mw.genie.co.kr/detail/albumInfo?axnm=83401557","retrieved":1672996457778,"image":"http://image.genie.co.kr/Y/IMAGE/IMG_ALBUM/083/401/557/83401557_1672988003812_1_200x200.JPG"},{"title":"Money (법쩐 X 정동하) (지니 모바일 ─ 최신음악)","contents":"정동하","link":"http://mw.genie.co.kr/detail/albumInfo?axnm=83401480","retrieved":1672996457784,"image":"http://image.genie.co.kr/Y/IMAGE/IMG_ALBUM/083/401/480/83401480_1672908655088_1_200x200.JPG"},{"title":"iScreaM Vol.20 : Forever Only (Remix) (지니 모바일 ─ 최신음악)","contents":"재현 (JAEHYUN) &amp; SHINDRUM","link":"http://mw.genie.co.kr/detail/albumInfo?axnm=83398677","retrieved":1672996457786,"image":"http://image.genie.co.kr/Y/IMAGE/IMG_ALBUM/083/398/677/83398677_1672987488626_1_200x200.JPG"},{"title":"지금은 아냐 (지니 모바일 ─ 최신음악)","contents":"줍에이 (Joob A)","link":"http://mw.genie.co.kr/detail/albumInfo?axnm=83394382","retrieved":1672996457789,"image":"http://image.genie.co.kr/Y/IMAGE/IMG_ALBUM/083/394/382/83394382_1672819975130_1_200x200.JPG"},{"title":"M1NUWORLD (지니 모바일 ─ 최신음악)","contents":"M1NU &amp; WIz World","link":"http://mw.genie.co.kr/detail/albumInfo?axnm=83401115","retrieved":1672996457790,"image":"http://image.genie.co.kr/Y/IMAGE/IMG_ALBUM/083/401/115/83401115_1672887327118_1_200x200.JPG"},{"title":"MEVIUS (지니 모바일 ─ 최신음악)","contents":"제이키 (J;KEY)","link":"http://mw.genie.co.kr/detail/albumInfo?axnm=83398692","retrieved":1672996457790,"image":"http://image.genie.co.kr/Y/IMAGE/IMG_ALBUM/083/398/692/83398692_1672824027440_1_200x200.JPG"}]}