{"title":"Combined feed","url":"https://MusicReleaseKR.github.io/genie/all.xml","elements":[{"title":"기억해줘 (지니 모바일 ─ 최신음악)","contents":"정지아","link":"http://mw.genie.co.kr/detail/albumInfo?axnm=83424779","retrieved":1673925363121,"image":"http://image.genie.co.kr/Y/IMAGE/IMG_ALBUM/083/424/779/83424779_1673839396936_1_200x200.JPG"},{"title":"소소한 이야기 Part.14 (지니 모바일 ─ 최신음악)","contents":"새벽공방","link":"http://mw.genie.co.kr/detail/albumInfo?axnm=83428792","retrieved":1673925363126,"image":"http://image.genie.co.kr/Y/IMAGE/IMG_ALBUM/083/428/792/83428792_1673855145791_1_200x200.JPG"},{"title":"미씽 : 그들이 있었다2 OST Part.4 (지니 모바일 ─ 최신음악)","contents":"김찬호","link":"http://mw.genie.co.kr/detail/albumInfo?axnm=83440831","retrieved":1673925363129,"image":"http://image.genie.co.kr/Y/IMAGE/IMG_ALBUM/083/440/831/83440831_1673858994475_1_200x200.JPG"},{"title":"i'm a mess (지니 모바일 ─ 최신음악)","contents":"SHIRT","link":"http://mw.genie.co.kr/detail/albumInfo?axnm=83440208","retrieved":1673925363132,"image":"http://image.genie.co.kr/Y/IMAGE/IMG_ALBUM/083/440/208/83440208_1673855154746_1_200x200.JPG"},{"title":"들을 노래 없을 때 듣는 노래 (지니 모바일 ─ 최신음악)","contents":"메리애플","link":"http://mw.genie.co.kr/detail/albumInfo?axnm=83440744","retrieved":1673925363135,"image":"http://image.genie.co.kr/Y/IMAGE/IMG_ALBUM/083/440/744/83440744_1673918442003_1_200x200.JPG"},{"title":"Pairing (지니 모바일 ─ 최신음악)","contents":"필름사운드","link":"http://mw.genie.co.kr/detail/albumInfo?axnm=83430002","retrieved":1673925363154,"image":"http://image.genie.co.kr/Y/IMAGE/IMG_ALBUM/083/430/002/83430002_1673860475652_1_200x200.JPG"},{"title":"그때, 우리 (지니 모바일 ─ 최신음악)","contents":"서민영","link":"http://mw.genie.co.kr/detail/albumInfo?axnm=83419423","retrieved":1673925363156,"image":"http://image.genie.co.kr/Y/IMAGE/IMG_ALBUM/083/419/423/83419423_1673847951880_1_200x200.JPG"},{"title":"Raptoad (지니 모바일 ─ 최신음악)","contents":"GGM Soulja","link":"http://mw.genie.co.kr/detail/albumInfo?axnm=83440248","retrieved":1673925363158,"image":"http://image.genie.co.kr/Y/IMAGE/IMG_ALBUM/083/440/248/83440248_1673921524222_1_200x200.JPG"},{"title":"Action (지니 모바일 ─ 최신음악)","contents":"COZI","link":"http://mw.genie.co.kr/detail/albumInfo?axnm=83423243","retrieved":1673925363164,"image":"http://image.genie.co.kr/Y/IMAGE/IMG_ALBUM/083/423/243/83423243_1673464584070_1_200x200.JPG"},{"title":"올해, 우리 활짝 필 수 있을거야 (지니 모바일 ─ 최신음악)","contents":"모레 (more)","link":"http://mw.genie.co.kr/detail/albumInfo?axnm=83425172","retrieved":1673925363165,"image":"http://image.genie.co.kr/Y/IMAGE/IMG_ALBUM/083/425/172/83425172_1673919203955_1_200x200.JPG"},{"title":"Love War (지니 모바일 ─ 최신음악)","contents":"YENA (최예나)","link":"http://mw.genie.co.kr/detail/albumInfo?axnm=83424630","retrieved":1673860516340,"image":"http://image.genie.co.kr/Y/IMAGE/IMG_ALBUM/083/424/630/83424630_1673833704395_1_200x200.JPG"},{"title":"Stamp On It - The 1st Mini Album (지니 모바일 ─ 최신음악)","contents":"GOT the beat","link":"http://mw.genie.co.kr/detail/albumInfo?axnm=83397213","retrieved":1673860516351,"image":"http://image.genie.co.kr/Y/IMAGE/IMG_ALBUM/083/397/213/83397213_1673851863778_1_200x200.JPG"},{"title":"따뜻한 꿈 (지니 모바일 ─ 최신음악)","contents":"SUN KIM","link":"http://mw.genie.co.kr/detail/albumInfo?axnm=83377013","retrieved":1673860516341,"image":"http://image.genie.co.kr/Y/IMAGE/IMG_ALBUM/083/377/013/83377013_1673585161335_1_200x200.JPG"},{"title":"Best Friend (지니 모바일 ─ 최신음악)","contents":"SUMIN (수민)","link":"http://mw.genie.co.kr/detail/albumInfo?axnm=83428951","retrieved":1673860516353,"image":"http://image.genie.co.kr/Y/IMAGE/IMG_ALBUM/083/428/951/83428951_1673579154927_1_200x200.JPG"},{"title":"시간을 여행하는 히치하이커를 위한 안내서 Part.1 (지니 모바일 ─ 최신음악)","contents":"찰리빈웍스","link":"http://mw.genie.co.kr/detail/albumInfo?axnm=83429849","retrieved":1673860516354,"image":"http://image.genie.co.kr/Y/IMAGE/IMG_ALBUM/083/429/849/83429849_1673603692232_1_200x200.JPG"},{"title":"i가E로 (지니 모바일 ─ 최신음악)","contents":"SOONHO (순호)","link":"http://mw.genie.co.kr/detail/albumInfo?axnm=83419296","retrieved":1673860516361,"image":"http://image.genie.co.kr/Y/IMAGE/IMG_ALBUM/083/419/296/83419296_1673849854863_1_200x200.JPG"},{"title":"이젠 너를 놓을게 (지니 모바일 ─ 최신음악)","contents":"에피타이저 (Appetizer)","link":"http://mw.genie.co.kr/detail/albumInfo?axnm=83440231","retrieved":1673860516361,"image":"http://image.genie.co.kr/Y/IMAGE/IMG_ALBUM/083/440/231/83440231_1673854378268_1_200x200.JPG"},{"title":"Wake Up (지니 모바일 ─ 최신음악)","contents":"한희준","link":"http://mw.genie.co.kr/detail/albumInfo?axnm=83425527","retrieved":1673838954987,"image":"http://image.genie.co.kr/Y/IMAGE/IMG_ALBUM/083/425/527/83425527_1673833021691_1_200x200.JPG"},{"title":"Cosmic Love Vol.1 (지니 모바일 ─ 최신음악)","contents":"Jxxn (진)","link":"http://mw.genie.co.kr/detail/albumInfo?axnm=83421241","retrieved":1673838954990,"image":"http://image.genie.co.kr/Y/IMAGE/IMG_ALBUM/083/421/241/83421241_1673585222171_1_200x200.JPG"},{"title":"수상한 작업실 Episode 2 (지니 모바일 ─ 최신음악)","contents":"에일리 (Ailee)","link":"http://mw.genie.co.kr/detail/albumInfo?axnm=83421975","retrieved":1673838954991,"image":"http://image.genie.co.kr/Y/IMAGE/IMG_ALBUM/083/421/975/83421975_1673518654032_1_200x200.JPG"}]}