{"title":"Combined feed","url":"https://MusicReleaseKR.github.io/genie/all.xml","elements":[{"title":"when the stars align (지니 모바일 ─ 최신음악)","contents":"윤새 (Yunsae)","link":"http://mw.genie.co.kr/detail/albumInfo?axnm=83548329","retrieved":1676863246444,"image":"http://image.genie.co.kr/Y/IMAGE/IMG_ALBUM/083/548/329/83548329_1676855406165_1_200x200.JPG"},{"title":"fall with me (지니 모바일 ─ 최신음악)","contents":"oftn (오픈)","link":"http://mw.genie.co.kr/detail/albumInfo?axnm=83550518","retrieved":1676863246446,"image":"http://image.genie.co.kr/Y/IMAGE/IMG_ALBUM/083/550/518/83550518_1676616626276_1_200x200.JPG"},{"title":"smallthing (지니 모바일 ─ 최신음악)","contents":"dori","link":"http://mw.genie.co.kr/detail/albumInfo?axnm=83556030","retrieved":1676863246448,"image":"http://image.genie.co.kr/Y/IMAGE/IMG_ALBUM/083/556/030/83556030_1676611081752_1_200x200.JPG"},{"title":"다시 가자 (지니 모바일 ─ 최신음악)","contents":"주윤하","link":"http://mw.genie.co.kr/detail/albumInfo?axnm=83550860","retrieved":1676863246449,"image":"http://image.genie.co.kr/Y/IMAGE/IMG_ALBUM/083/550/860/83550860_1676604412599_1_200x200.JPG"},{"title":"CURE (지니 모바일 ─ 최신음악)","contents":"백성현","link":"http://mw.genie.co.kr/detail/albumInfo?axnm=83563455","retrieved":1676863246455,"image":"http://image.genie.co.kr/Y/IMAGE/IMG_ALBUM/083/563/455/83563455_1676859072071_1_200x200.JPG"},{"title":"Thrill (지니 모바일 ─ 최신음악)","contents":"엘라스트 (E'LAST)","link":"http://mw.genie.co.kr/detail/albumInfo?axnm=83548454","retrieved":1676863246455,"image":"http://image.genie.co.kr/Y/IMAGE/IMG_ALBUM/083/548/454/83548454_1676543158058_1_200x200.JPG"},{"title":"압구정 (Apgujeong) (지니 모바일 ─ 최신음악)","contents":"Jiho Givenchy (지호지방시)","link":"http://mw.genie.co.kr/detail/albumInfo?axnm=83556169","retrieved":1676863246456,"image":"http://image.genie.co.kr/Y/IMAGE/IMG_ALBUM/083/556/169/83556169_1676624445271_1_200x200.JPG"},{"title":"Gardener (지니 모바일 ─ 최신음악)","contents":"이날 (YNR)","link":"http://mw.genie.co.kr/detail/albumInfo?axnm=83556183","retrieved":1676863246458,"image":"http://image.genie.co.kr/Y/IMAGE/IMG_ALBUM/083/556/183/83556183_1676622773413_1_200x200.JPG"},{"title":"어쩌다 이별 (지니 모바일 ─ 최신음악)","contents":"유다원","link":"http://mw.genie.co.kr/detail/albumInfo?axnm=83550396","retrieved":1676863246458,"image":"http://image.genie.co.kr/Y/IMAGE/IMG_ALBUM/083/550/396/83550396_1676856049721_1_200x200.JPG"},{"title":"ㄴㄴ (지니 모바일 ─ 최신음악)","contents":"HYUN SEO","link":"http://mw.genie.co.kr/detail/albumInfo?axnm=83550451","retrieved":1676863246458,"image":"http://image.genie.co.kr/Y/IMAGE/IMG_ALBUM/083/550/451/83550451_1676439638528_1_200x200.JPG"},{"title":"Light Switch (지니 모바일 ─ 최신음악)","contents":"xooos (수스)","link":"http://mw.genie.co.kr/detail/albumInfo?axnm=83552140","retrieved":1676863246458,"image":"http://image.genie.co.kr/Y/IMAGE/IMG_ALBUM/083/552/140/83552140_1676856245711_1_200x200.JPG"},{"title":"꿈속을 걸어요 (지니 모바일 ─ 최신음악)","contents":"제이디 (JD)","link":"http://mw.genie.co.kr/detail/albumInfo?axnm=83552884","retrieved":1676863246460,"image":"http://image.genie.co.kr/Y/IMAGE/IMG_ALBUM/083/552/884/83552884_1676800967477_1_200x200.JPG"},{"title":"꽃이 저문다 (지니 모바일 ─ 최신음악)","contents":"#안녕","link":"http://mw.genie.co.kr/detail/albumInfo?axnm=83545190","retrieved":1676798070441,"image":"http://image.genie.co.kr/Y/IMAGE/IMG_ALBUM/083/545/190/83545190_1676616359728_1_200x200.JPG"},{"title":"영원 (Forever) (지니 모바일 ─ 최신음악)","contents":"정동원 (Jeong Dong Won)","link":"http://mw.genie.co.kr/detail/albumInfo?axnm=83552637","retrieved":1676798070445,"image":"http://image.genie.co.kr/Y/IMAGE/IMG_ALBUM/083/552/637/83552637_1676609378888_1_200x200.JPG"},{"title":"결 (Attitude) #4 (지니 모바일 ─ 최신음악)","contents":"공기남","link":"http://mw.genie.co.kr/detail/albumInfo?axnm=83552136","retrieved":1676798070445,"image":"http://image.genie.co.kr/Y/IMAGE/IMG_ALBUM/083/552/136/83552136_1676624624391_1_200x200.JPG"},{"title":"빨간풍선 OST Part.7 (지니 모바일 ─ 최신음악)","contents":"정동하","link":"http://mw.genie.co.kr/detail/albumInfo?axnm=83555460","retrieved":1676798070445,"image":"http://image.genie.co.kr/Y/IMAGE/IMG_ALBUM/083/555/460/83555460_1676603471261_1_200x200.JPG"},{"title":"삼남매가 용감하게 OST Part.11 (지니 모바일 ─ 최신음악)","contents":"버나드 박","link":"http://mw.genie.co.kr/detail/albumInfo?axnm=83552417","retrieved":1676798070445,"image":"http://image.genie.co.kr/Y/IMAGE/IMG_ALBUM/083/552/417/83552417_1676527028029_1_200x200.JPG"},{"title":"연애의 참견 2023 OST - Part.4 (지니 모바일 ─ 최신음악)","contents":"다람","link":"http://mw.genie.co.kr/detail/albumInfo?axnm=83555600","retrieved":1676798070447,"image":"http://image.genie.co.kr/Y/IMAGE/IMG_ALBUM/083/555/600/83555600_1676614042536_1_200x200.JPG"},{"title":"심 (心) (지니 모바일 ─ 최신음악)","contents":"DK (디셈버)","link":"http://mw.genie.co.kr/detail/albumInfo?axnm=83556186","retrieved":1676798070452,"image":"http://image.genie.co.kr/Y/IMAGE/IMG_ALBUM/083/556/186/83556186_1676621348326_1_200x200.JPG"},{"title":"뭘해도 예뻐 (지니 모바일 ─ 최신음악)","contents":"비비 (BB)","link":"http://mw.genie.co.kr/detail/albumInfo?axnm=83552569","retrieved":1676798070453,"image":"http://image.genie.co.kr/Y/IMAGE/IMG_ALBUM/083/552/569/83552569_1676611948254_1_200x200.JPG"}]}