{"title":"Combined feed","url":"https://MusicReleaseKR.github.io/genie/all.xml","elements":[{"title":"Turtle (지니 모바일 ─ 최신음악)","contents":"Cha","link":"http://mw.genie.co.kr/detail/albumInfo?axnm=82602591","retrieved":1648178424421,"image":"http://image.genie.co.kr/Y/IMAGE/IMG_ALBUM/082/602/591/82602591_1648106978974_1_200x200.JPG"},{"title":"GABRIEL (Korean Special Edition) (지니 모바일 ─ 최신음악)","contents":"Keshi","link":"http://mw.genie.co.kr/detail/albumInfo?axnm=82514313","retrieved":1648178424423,"image":"http://image.genie.co.kr/Y/IMAGE/IMG_ALBUM/082/514/313/82514313_1648098143752_1_200x200.JPG"},{"title":"SeoulVibes, SEESAW (지니 모바일 ─ 최신음악)","contents":"KozyPop","link":"http://mw.genie.co.kr/detail/albumInfo?axnm=82602760","retrieved":1648178424423,"image":"http://image.genie.co.kr/Y/IMAGE/IMG_ALBUM/082/602/760/82602760_1648117789749_1_200x200.JPG"},{"title":"하나만 주세요 (지니 모바일 ─ 최신음악)","contents":"다루","link":"http://mw.genie.co.kr/detail/albumInfo?axnm=82599265","retrieved":1648178424426,"image":"http://image.genie.co.kr/Y/IMAGE/IMG_ALBUM/082/599/265/82599265_1648096392886_1_200x200.JPG"},{"title":"도망쳐 (지니 모바일 ─ 최신음악)","contents":"리코 (Rico)","link":"http://mw.genie.co.kr/detail/albumInfo?axnm=82604622","retrieved":1648178424426,"image":"http://image.genie.co.kr/Y/IMAGE/IMG_ALBUM/082/604/622/82604622_1648169894501_1_200x200.JPG"},{"title":"매일매일 (지니 모바일 ─ 최신음악)","contents":"위아더나잇 (We Are The Night)","link":"http://mw.genie.co.kr/detail/albumInfo?axnm=82603101","retrieved":1648178424427,"image":"http://image.genie.co.kr/Y/IMAGE/IMG_ALBUM/082/603/101/82603101_1648171512302_1_200x200.JPG"},{"title":"Lovely Day (지니 모바일 ─ 최신음악)","contents":"에스나 (eSNa)","link":"http://mw.genie.co.kr/detail/albumInfo?axnm=82604648","retrieved":1648178424427,"image":"http://image.genie.co.kr/Y/IMAGE/IMG_ALBUM/082/604/648/82604648_1648101630246_1_200x200.JPG"},{"title":"국가가 부른다 Part5 (지니 모바일 ─ 최신음악)","contents":"Various Artists","link":"http://mw.genie.co.kr/detail/albumInfo?axnm=82604287","retrieved":1648178424441,"image":"http://image.genie.co.kr/Y/IMAGE/IMG_ALBUM/082/604/287/82604287_1648115827789_1_200x200.JPG"},{"title":"PIECE-2 : 타미즈 (지니 모바일 ─ 최신음악)","contents":"THE PIECES (더 피스)","link":"http://mw.genie.co.kr/detail/albumInfo?axnm=82604504","retrieved":1648178424443,"image":"http://image.genie.co.kr/Y/IMAGE/IMG_ALBUM/082/604/504/82604504_1648111807652_1_200x200.JPG"},{"title":"연대기 (지니 모바일 ─ 최신음악)","contents":"장필순","link":"http://mw.genie.co.kr/detail/albumInfo?axnm=82604803","retrieved":1648178424449,"image":"http://image.genie.co.kr/Y/IMAGE/IMG_ALBUM/082/604/803/82604803_1648115429680_1_200x200.JPG"},{"title":"The Last Thing Left (지니 모바일 ─ 최신음악)","contents":"세이수미","link":"http://mw.genie.co.kr/detail/albumInfo?axnm=82586484","retrieved":1648178424449,"image":"http://image.genie.co.kr/Y/IMAGE/IMG_ALBUM/082/586/484/82586484_1648175313625_1_200x200.JPG"},{"title":"PROMISED LAND (지니 모바일 ─ 최신음악)","contents":"Paul Blanco","link":"http://mw.genie.co.kr/detail/albumInfo?axnm=82603072","retrieved":1648113674853,"image":"http://image.genie.co.kr/Y/IMAGE/IMG_ALBUM/082/603/072/82603072_1648104185420_1_200x200.JPG"},{"title":"이석훈 정규 1 '같은 자리' (지니 모바일 ─ 최신음악)","contents":"이석훈","link":"http://mw.genie.co.kr/detail/albumInfo?axnm=82603084","retrieved":1648113674856,"image":"http://image.genie.co.kr/Y/IMAGE/IMG_ALBUM/082/603/084/82603084_1648100976520_1_200x200.JPG"},{"title":"킬힐 OST Part 2 (지니 모바일 ─ 최신음악)","contents":"일레인","link":"http://mw.genie.co.kr/detail/albumInfo?axnm=82602888","retrieved":1648113674856,"image":"http://image.genie.co.kr/Y/IMAGE/IMG_ALBUM/082/602/888/82602888_1648103588279_1_200x200.JPG"},{"title":"나의 스웨덴세탁소 #2 (지니 모바일 ─ 최신음악)","contents":"송하영 (프로미스나인)","link":"http://mw.genie.co.kr/detail/albumInfo?axnm=82603125","retrieved":1648113674858,"image":"http://image.genie.co.kr/Y/IMAGE/IMG_ALBUM/082/603/125/82603125_1648103249585_1_200x200.JPG"},{"title":"시작 (Push & pull) (지니 모바일 ─ 최신음악)","contents":"김필","link":"http://mw.genie.co.kr/detail/albumInfo?axnm=82599280","retrieved":1648113674864,"image":"http://image.genie.co.kr/Y/IMAGE/IMG_ALBUM/082/599/280/82599280_1648023073008_1_200x200.JPG"},{"title":"서른, 아홉 OST Part.6 (지니 모바일 ─ 최신음악)","contents":"정준일","link":"http://mw.genie.co.kr/detail/albumInfo?axnm=82602871","retrieved":1648113674870,"image":"http://image.genie.co.kr/Y/IMAGE/IMG_ALBUM/082/602/871/82602871_1648100413992_1_200x200.JPG"},{"title":"MOBYDICK (지니 모바일 ─ 최신음악)","contents":"시네마 (CNEMA)","link":"http://mw.genie.co.kr/detail/albumInfo?axnm=82602699","retrieved":1648113674871,"image":"http://image.genie.co.kr/Y/IMAGE/IMG_ALBUM/082/602/699/82602699_1648103600354_1_200x200.JPG"},{"title":"howtosurvive_____ (지니 모바일 ─ 최신음악)","contents":"SINDOSI : 22","link":"http://mw.genie.co.kr/detail/albumInfo?axnm=82599592","retrieved":1648113674871,"image":"http://image.genie.co.kr/Y/IMAGE/IMG_ALBUM/082/599/592/82599592_1647877560909_1_200x200.JPG"},{"title":"겨울 지나 벚꽃 OST PART.5 (지니 모바일 ─ 최신음악)","contents":"태호 (TAE HO)","link":"http://mw.genie.co.kr/detail/albumInfo?axnm=82591728","retrieved":1648113674872,"image":"http://image.genie.co.kr/Y/IMAGE/IMG_ALBUM/082/591/728/82591728_1648015101509_1_200x200.JPG"}]}