{"title":"지니 모바일 ─ 최신음악","url":"http://mw.genie.co.kr/newest","favicon":"http://mw.genie.co.kr/favicon.ico","elements":[{"title":"Restart : 20th","contents":"KCM","link":"http://mw.genie.co.kr/detail/albumInfo?axnm=83794128","retrieved":1683710016547,"image":"http://image.genie.co.kr/Y/IMAGE/IMG_ALBUM/083/794/128/83794128_1683618134653_1_200x200.JPG"},{"title":"오늘보다 내일 더욱","contents":"DOKO (도코) &amp; 임사랑","link":"http://mw.genie.co.kr/detail/albumInfo?axnm=83808114","retrieved":1683710016549,"image":"http://image.genie.co.kr/Y/IMAGE/IMG_ALBUM/083/808/114/83808114_1683605099573_1_200x200.JPG"},{"title":"나쁜엄마 OST Part.4","contents":"멜로망스 (MeloMance)","link":"http://mw.genie.co.kr/detail/albumInfo?axnm=83810571","retrieved":1683710016553,"image":"http://image.genie.co.kr/Y/IMAGE/IMG_ALBUM/083/810/571/83810571_1683627953198_1_200x200.JPG"},{"title":"YOUNHA Studio Live Album 'MINDSET'","contents":"윤하 (YOUNHA)","link":"http://mw.genie.co.kr/detail/albumInfo?axnm=83807792","retrieved":1683710016556,"image":"http://image.genie.co.kr/Y/IMAGE/IMG_ALBUM/083/807/792/83807792_1683683369849_1_200x200.JPG"},{"title":"사랑이 따끔 (Lovesick)","contents":"성민 (SUNGMIN)","link":"http://mw.genie.co.kr/detail/albumInfo?axnm=83811825","retrieved":1683710016556,"image":"http://image.genie.co.kr/Y/IMAGE/IMG_ALBUM/083/811/825/83811825_1683686008072_1_200x200.JPG"},{"title":"Recall of memories","contents":"이우","link":"http://mw.genie.co.kr/detail/albumInfo?axnm=83807586","retrieved":1683710016556,"image":"http://image.genie.co.kr/Y/IMAGE/IMG_ALBUM/083/807/586/83807586_1683685128427_1_200x200.JPG"},{"title":"Bad ideas","contents":"라 블랑캣 (La Blancat)","link":"http://mw.genie.co.kr/detail/albumInfo?axnm=83809970","retrieved":1683710016560,"image":"http://image.genie.co.kr/Y/IMAGE/IMG_ALBUM/083/809/970/83809970_1683608007815_1_200x200.JPG"},{"title":"이게 마지막","contents":"안재우","link":"http://mw.genie.co.kr/detail/albumInfo?axnm=83807593","retrieved":1683710016561,"image":"http://image.genie.co.kr/Y/IMAGE/IMG_ALBUM/083/807/593/83807593_1683622683499_1_200x200.JPG"},{"title":"FEELING!","contents":"Otis Lim","link":"http://mw.genie.co.kr/detail/albumInfo?axnm=83762681","retrieved":1683710016561,"image":"http://image.genie.co.kr/Y/IMAGE/IMG_ALBUM/083/762/681/83762681_1683680723059_1_200x200.JPG"},{"title":"하루종일","contents":"서로이","link":"http://mw.genie.co.kr/detail/albumInfo?axnm=83808418","retrieved":1683688471462,"image":"http://image.genie.co.kr/Y/IMAGE/IMG_ALBUM/083/808/418/83808418_1683617900878_1_200x200.JPG"},{"title":"알고보니 혼수상태 가요제 우승자 특전곡","contents":"박서진","link":"http://mw.genie.co.kr/detail/albumInfo?axnm=83807989","retrieved":1683688471472,"image":"http://image.genie.co.kr/Y/IMAGE/IMG_ALBUM/083/807/989/83807989_1683619094488_1_200x200.JPG"},{"title":"돌 아 오 지 마","contents":"Mingginyu (밍기뉴)","link":"http://mw.genie.co.kr/detail/albumInfo?axnm=83797290","retrieved":1683688471472,"image":"http://image.genie.co.kr/Y/IMAGE/IMG_ALBUM/083/797/290/83797290_1683531041792_1_200x200.JPG"},{"title":"Life In LA","contents":"Mix.audio &amp; Dbo (디보)","link":"http://mw.genie.co.kr/detail/albumInfo?axnm=83799581","retrieved":1683688471473,"image":"http://image.genie.co.kr/Y/IMAGE/IMG_ALBUM/083/799/581/83799581_1683594361698_1_200x200.JPG"},{"title":"MBC 일일드라마 '하늘의 인연' OST Part.2","contents":"숙희","link":"http://mw.genie.co.kr/detail/albumInfo?axnm=83809797","retrieved":1683688471476,"image":"http://image.genie.co.kr/Y/IMAGE/IMG_ALBUM/083/809/797/83809797_1683624091213_1_200x200.JPG"},{"title":"에루화","contents":"양반들 (Yangbans)","link":"http://mw.genie.co.kr/detail/albumInfo?axnm=83779436","retrieved":1683688471476,"image":"http://image.genie.co.kr/Y/IMAGE/IMG_ALBUM/083/779/436/83779436_1683618934362_1_200x200.JPG"},{"title":"말해주라","contents":"소수빈","link":"http://mw.genie.co.kr/detail/albumInfo?axnm=83808663","retrieved":1683688471476,"image":"http://image.genie.co.kr/Y/IMAGE/IMG_ALBUM/083/808/663/83808663_1683623132723_1_200x200.JPG"},{"title":"이별이 참 아프니까","contents":"여은","link":"http://mw.genie.co.kr/detail/albumInfo?axnm=83808428","retrieved":1683688471485,"image":"http://image.genie.co.kr/Y/IMAGE/IMG_ALBUM/083/808/428/83808428_1683614144443_1_200x200.JPG"},{"title":"glitter eyes","contents":"SEINY","link":"http://mw.genie.co.kr/detail/albumInfo?axnm=83809760","retrieved":1683688471493,"image":"http://image.genie.co.kr/Y/IMAGE/IMG_ALBUM/083/809/760/83809760_1683596427204_1_200x200.JPG"},{"title":"Lonely man but sweet man","contents":"최항석과 부기몬스터","link":"http://mw.genie.co.kr/detail/albumInfo?axnm=83797374","retrieved":1683688471493,"image":"http://image.genie.co.kr/Y/IMAGE/IMG_ALBUM/083/797/374/83797374_1683092435985_1_200x200.JPG"},{"title":"아이마미따 (Ay Mamita)","contents":"유준상 &amp; 로민 &amp; 원준","link":"http://mw.genie.co.kr/detail/albumInfo?axnm=83800628","retrieved":1683688471493,"image":"http://image.genie.co.kr/Y/IMAGE/IMG_ALBUM/083/800/628/83800628_1683197779343_1_200x200.JPG"}]}