{"title":"지니 모바일 ─ 최신음악","url":"http://mw.genie.co.kr/newest","favicon":"http://mw.genie.co.kr/favicon.ico","elements":[{"title":"K'up","contents":"던말릭 (DON MALIK)","link":"http://mw.genie.co.kr/detail/albumInfo?axnm=84804650","retrieved":1708074772767,"image":"https://image.genie.co.kr/Y/IMAGE/IMG_ALBUM/084/804/650/84804650_1708048319383_1_200x200.JPG"},{"title":"The Young Man and the Deep Sea","contents":"임현식 (비투비)","link":"http://mw.genie.co.kr/detail/albumInfo?axnm=84804567","retrieved":1708074772768,"image":"https://image.genie.co.kr/Y/IMAGE/IMG_ALBUM/084/804/567/84804567_1707988644439_1_200x200.JPG"},{"title":"yes, and?","contents":"Ariana Grande &amp; Mariah Carey","link":"http://mw.genie.co.kr/detail/albumInfo?axnm=84808213","retrieved":1708060401476,"image":"https://image.genie.co.kr/Y/IMAGE/IMG_ALBUM/084/808/213/84808213_1708064788201_1_200x200.JPG"},{"title":"손오공 (Workout Remix)","contents":"세븐틴 (SEVENTEEN)","link":"http://mw.genie.co.kr/detail/albumInfo?axnm=84805135","retrieved":1708060401489,"image":"https://image.genie.co.kr/Y/IMAGE/IMG_ALBUM/084/805/135/84805135_1707976299633_1_200x200.JPG"},{"title":"남과여 OST Part.5","contents":"jeebanoff (지바노프)","link":"http://mw.genie.co.kr/detail/albumInfo?axnm=84804705","retrieved":1708074772773,"image":"https://image.genie.co.kr/Y/IMAGE/IMG_ALBUM/084/804/705/84804705_1708048317684_1_200x200.JPG"},{"title":"재벌X형사 OST Part.3","contents":"버나드 박","link":"http://mw.genie.co.kr/detail/albumInfo?axnm=84804963","retrieved":1708074772773,"image":"https://image.genie.co.kr/Y/IMAGE/IMG_ALBUM/084/804/963/84804963_1708068168760_1_200x200.JPG"},{"title":"어떻게 잊어요","contents":"정창룡","link":"http://mw.genie.co.kr/detail/albumInfo?axnm=84805365","retrieved":1708074772773,"image":"https://image.genie.co.kr/Y/IMAGE/IMG_ALBUM/084/805/365/84805365_1707989816768_1_200x200.JPG"},{"title":"사노라면","contents":"정다경","link":"http://mw.genie.co.kr/detail/albumInfo?axnm=84805175","retrieved":1708074772775,"image":"https://image.genie.co.kr/Y/IMAGE/IMG_ALBUM/084/805/175/84805175_1707988649638_1_200x200.JPG"},{"title":"그래도 괜찮아","contents":"전철민","link":"http://mw.genie.co.kr/detail/albumInfo?axnm=84805520","retrieved":1708074772776,"image":"https://image.genie.co.kr/Y/IMAGE/IMG_ALBUM/084/805/520/84805520_1708048926509_1_200x200.JPG"},{"title":"아이스 아메리카노","contents":"윤언니","link":"http://mw.genie.co.kr/detail/albumInfo?axnm=84798313","retrieved":1708074772777,"image":"https://image.genie.co.kr/Y/IMAGE/IMG_ALBUM/084/798/313/84798313_1707890514704_1_200x200.JPG"},{"title":"ZR","contents":"dramabo!damovie","link":"http://mw.genie.co.kr/detail/albumInfo?axnm=84797692","retrieved":1708074772779,"image":"https://image.genie.co.kr/Y/IMAGE/IMG_ALBUM/084/797/692/84797692_1707986593148_1_200x200.JPG"},{"title":"가로등 아래에서","contents":"Western P.I.G","link":"http://mw.genie.co.kr/detail/albumInfo?axnm=84781151","retrieved":1708053297728,"image":"https://image.genie.co.kr/Y/IMAGE/IMG_ALBUM/084/781/151/84781151_1707982653349_1_200x200.JPG"},{"title":"Training Season","contents":"Dua Lipa","link":"http://mw.genie.co.kr/detail/albumInfo?axnm=84804158","retrieved":1708038801716,"image":"https://image.genie.co.kr/Y/IMAGE/IMG_ALBUM/084/804/158/84804158_1707947229547_1_200x200.JPG"},{"title":"Worlds Apart","contents":"플로우식 (Flowsik)","link":"http://mw.genie.co.kr/detail/albumInfo?axnm=84727777","retrieved":1708053297730,"image":"https://image.genie.co.kr/Y/IMAGE/IMG_ALBUM/084/727/777/84727777_1705905729703_1_200x200.JPG"},{"title":"어떤가요","contents":"이정봉 &amp; 장리인 (Zhang Li Yin)","link":"http://mw.genie.co.kr/detail/albumInfo?axnm=84798662","retrieved":1708053297748,"image":"https://image.genie.co.kr/Y/IMAGE/IMG_ALBUM/084/798/662/84798662_1708046158512_1_200x200.JPG"},{"title":"미스트롯3 라이벌매치 삼각대전","contents":"Various Artists","link":"http://mw.genie.co.kr/detail/albumInfo?axnm=84804506","retrieved":1708053297748,"image":"https://image.genie.co.kr/Y/IMAGE/IMG_ALBUM/084/804/506/84804506_1707988631597_1_200x200.JPG"},{"title":"LOVE IN STEREO","contents":"MAX","link":"http://mw.genie.co.kr/detail/albumInfo?axnm=84800430","retrieved":1708009996429,"image":"https://image.genie.co.kr/Y/IMAGE/IMG_ALBUM/084/800/430/84800430_1707845200892_1_200x200.JPG"},{"title":"5월의 밤","contents":"하츠 (hartts)","link":"http://mw.genie.co.kr/detail/albumInfo?axnm=84804485","retrieved":1708053297754,"image":"https://image.genie.co.kr/Y/IMAGE/IMG_ALBUM/084/804/485/84804485_1707957998807_1_200x200.JPG"},{"title":"밤에 피는 꽃 OST Part.7","contents":"프린 (Prin)","link":"http://mw.genie.co.kr/detail/albumInfo?axnm=84801536","retrieved":1708053297754,"image":"https://image.genie.co.kr/Y/IMAGE/IMG_ALBUM/084/801/536/84801536_1707988640871_1_200x200.JPG"},{"title":"ARTIST. moonO=","contents":"Anonymous Artists (어나니머스 아티스트)","link":"http://mw.genie.co.kr/detail/albumInfo?axnm=84805285","retrieved":1708053297756,"image":"https://image.genie.co.kr/Y/IMAGE/IMG_ALBUM/084/805/285/84805285_1708047732695_1_200x200.JPG"}]}