{"title":"지니 모바일 ─ 최신음악","url":"http://mw.genie.co.kr/newest","favicon":"http://mw.genie.co.kr/favicon.ico","elements":[{"title":"돛단배","contents":"아롱","link":"http://mw.genie.co.kr/detail/albumInfo?axnm=84518980","retrieved":1701227635934,"image":"https://image.genie.co.kr/Y/IMAGE/IMG_ALBUM/084/518/980/84518980_1700729636406_1_200x200.JPG"},{"title":"멋있게 살아줘","contents":"이지형","link":"http://mw.genie.co.kr/detail/albumInfo?axnm=84539840","retrieved":1701227635942,"image":"https://image.genie.co.kr/Y/IMAGE/IMG_ALBUM/084/539/840/84539840_1701161006441_1_200x200.JPG"},{"title":"현역가왕 예선전 PART 1","contents":"Various Artists","link":"http://mw.genie.co.kr/detail/albumInfo?axnm=84545214","retrieved":1701227635942,"image":"https://image.genie.co.kr/Y/IMAGE/IMG_ALBUM/084/545/214/84545214_1701219911072_1_200x200.JPG"},{"title":"오늘도 사랑스럽개 OST Part. 4 : 상상","contents":"별은","link":"http://mw.genie.co.kr/detail/albumInfo?axnm=84540553","retrieved":1701227635943,"image":"https://image.genie.co.kr/Y/IMAGE/IMG_ALBUM/084/540/553/84540553_1701151654569_1_200x200.JPG"},{"title":"Merry X-marx","contents":"전자양","link":"http://mw.genie.co.kr/detail/albumInfo?axnm=84535398","retrieved":1701227635948,"image":"https://image.genie.co.kr/Y/IMAGE/IMG_ALBUM/084/535/398/84535398_1701152518194_1_200x200.JPG"},{"title":"Project XPU.PLANET Vol.1","contents":"변진섭","link":"http://mw.genie.co.kr/detail/albumInfo?axnm=84498521","retrieved":1701227635948,"image":"https://image.genie.co.kr/Y/IMAGE/IMG_ALBUM/084/498/521/84498521_1701072616134_1_200x200.JPG"},{"title":"있잖아","contents":"wurii (우리)","link":"http://mw.genie.co.kr/detail/albumInfo?axnm=84540660","retrieved":1701227635953,"image":"https://image.genie.co.kr/Y/IMAGE/IMG_ALBUM/084/540/660/84540660_1701160301706_1_200x200.JPG"},{"title":"사랑한다고 말해줘 OST Part 1","contents":"Seori","link":"http://mw.genie.co.kr/detail/albumInfo?axnm=84529032","retrieved":1701162842469,"image":"https://image.genie.co.kr/Y/IMAGE/IMG_ALBUM/084/529/032/84529032_1701075933759_1_200x200.JPG"},{"title":"12월","contents":"SEINY","link":"http://mw.genie.co.kr/detail/albumInfo?axnm=84544902","retrieved":1701227635954,"image":"https://image.genie.co.kr/Y/IMAGE/IMG_ALBUM/084/544/902/84544902_1701147030145_1_200x200.JPG"},{"title":"Messy Room","contents":"The Deep","link":"http://mw.genie.co.kr/detail/albumInfo?axnm=84540777","retrieved":1701227635954,"image":"https://image.genie.co.kr/Y/IMAGE/IMG_ALBUM/084/540/777/84540777_1701163171798_1_200x200.JPG"},{"title":"All I Want Is You","contents":"drewboi","link":"http://mw.genie.co.kr/detail/albumInfo?axnm=84540829","retrieved":1701227635973,"image":"https://image.genie.co.kr/Y/IMAGE/IMG_ALBUM/084/540/829/84540829_1701221507625_1_200x200.JPG"},{"title":"카세트","contents":"Thru","link":"http://mw.genie.co.kr/detail/albumInfo?axnm=84545260","retrieved":1701227635973,"image":"https://image.genie.co.kr/Y/IMAGE/IMG_ALBUM/084/545/260/84545260_1701163027351_1_200x200.JPG"},{"title":"My Ending Page","contents":"연경이","link":"http://mw.genie.co.kr/detail/albumInfo?axnm=84528949","retrieved":1701227635973,"image":"https://image.genie.co.kr/Y/IMAGE/IMG_ALBUM/084/528/949/84528949_1700791857837_1_200x200.JPG"},{"title":"Violet","contents":"한백","link":"http://mw.genie.co.kr/detail/albumInfo?axnm=84528652","retrieved":1701227635973,"image":"https://image.genie.co.kr/Y/IMAGE/IMG_ALBUM/084/528/652/84528652_1701148703278_1_200x200.JPG"},{"title":"내가 사랑했던 그대여","contents":"김민울","link":"http://mw.genie.co.kr/detail/albumInfo?axnm=84513135","retrieved":1701227635974,"image":"https://image.genie.co.kr/Y/IMAGE/IMG_ALBUM/084/513/135/84513135_1701160929345_1_200x200.JPG"},{"title":"잉어님과 떡볶이 OST Part.25","contents":"휴이 (Huie)","link":"http://mw.genie.co.kr/detail/albumInfo?axnm=84528443","retrieved":1701227635974,"image":"https://image.genie.co.kr/Y/IMAGE/IMG_ALBUM/084/528/443/84528443_1701150189150_1_200x200.JPG"},{"title":"Do you feel it too?","contents":"curv moon","link":"http://mw.genie.co.kr/detail/albumInfo?axnm=84540752","retrieved":1701227635974,"image":"https://image.genie.co.kr/Y/IMAGE/IMG_ALBUM/084/540/752/84540752_1701066335485_1_200x200.JPG"},{"title":"NASTY BUT TASTY","contents":"GUILTY PLEASURE (길티플레져)","link":"http://mw.genie.co.kr/detail/albumInfo?axnm=84526181","retrieved":1701227635975,"image":"https://image.genie.co.kr/Y/IMAGE/IMG_ALBUM/084/526/181/84526181_1700761827893_1_200x200.JPG"},{"title":"Dirty Jersey Duo II","contents":"키미 (kimmy) &amp; 칼 (KAL)","link":"http://mw.genie.co.kr/detail/albumInfo?axnm=84538211","retrieved":1701227635979,"image":"https://image.genie.co.kr/Y/IMAGE/IMG_ALBUM/084/538/211/84538211_1701160012492_1_200x200.JPG"},{"title":"HORMONE","contents":"TIZKOI","link":"http://mw.genie.co.kr/detail/albumInfo?axnm=84544945","retrieved":1701227635980,"image":"https://image.genie.co.kr/Y/IMAGE/IMG_ALBUM/084/544/945/84544945_1701151171544_1_200x200.JPG"}]}