{"title":"지니 모바일 ─ 최신음악","url":"http://mw.genie.co.kr/newest","favicon":"http://mw.genie.co.kr/favicon.ico","elements":[{"title":"Criminal","contents":"Street Baby","link":"http://mw.genie.co.kr/detail/albumInfo?axnm=82792447","retrieved":1656560520112,"image":"http://image.genie.co.kr/Y/IMAGE/IMG_ALBUM/082/792/447/82792447_1656475086448_1_200x200.JPG"},{"title":"그대 곁을 맴돌아","contents":"연규성","link":"http://mw.genie.co.kr/detail/albumInfo?axnm=82794678","retrieved":1656560520117,"image":"http://image.genie.co.kr/Y/IMAGE/IMG_ALBUM/082/794/678/82794678_1656493944728_1_200x200.JPG"},{"title":"I was a Hero","contents":"9001 (Ninety O One)","link":"http://mw.genie.co.kr/detail/albumInfo?axnm=82778776","retrieved":1656560520121,"image":"http://image.genie.co.kr/Y/IMAGE/IMG_ALBUM/082/778/776/82778776_1656500530157_1_200x200.JPG"},{"title":"유난히 아름다웠던","contents":"장들레","link":"http://mw.genie.co.kr/detail/albumInfo?axnm=82794451","retrieved":1656560520122,"image":"http://image.genie.co.kr/Y/IMAGE/IMG_ALBUM/082/794/451/82794451_1656554825332_1_200x200.JPG"},{"title":"Yellow Fever","contents":"Yonge Jaundice (영 잔디스)","link":"http://mw.genie.co.kr/detail/albumInfo?axnm=82793840","retrieved":1656560520127,"image":"http://image.genie.co.kr/Y/IMAGE/IMG_ALBUM/082/793/840/82793840_1656556089243_1_200x200.JPG"},{"title":"종말의 종말","contents":"조영현","link":"http://mw.genie.co.kr/detail/albumInfo?axnm=82792449","retrieved":1656560520128,"image":"http://image.genie.co.kr/Y/IMAGE/IMG_ALBUM/082/792/449/82792449_1656474786882_1_200x200.JPG"},{"title":"작전","contents":"스카이민혁 (Skyminhyuk) &amp; 필리","link":"http://mw.genie.co.kr/detail/albumInfo?axnm=82793807","retrieved":1656560520134,"image":"http://image.genie.co.kr/Y/IMAGE/IMG_ALBUM/082/793/807/82793807_1656555307621_1_200x200.JPG"},{"title":"돌아,가다","contents":"입술을깨물다","link":"http://mw.genie.co.kr/detail/albumInfo?axnm=82788788","retrieved":1656560520135,"image":"http://image.genie.co.kr/Y/IMAGE/IMG_ALBUM/082/788/788/82788788_1656472319331_1_200x200.JPG"},{"title":"록스타","contents":"공훈 (Gong Hoon)","link":"http://mw.genie.co.kr/detail/albumInfo?axnm=82758881","retrieved":1656560520136,"image":"http://image.genie.co.kr/Y/IMAGE/IMG_ALBUM/082/758/881/82758881_1656559446609_1_200x200.JPG"},{"title":"TAPE #01","contents":"Hollow Young &amp; TommyTheTrapKid","link":"http://mw.genie.co.kr/detail/albumInfo?axnm=82794708","retrieved":1656560520137,"image":"http://image.genie.co.kr/Y/IMAGE/IMG_ALBUM/082/794/708/82794708_1656483940424_1_200x200.JPG"},{"title":"수렴","contents":"Dutch Van","link":"http://mw.genie.co.kr/detail/albumInfo?axnm=82792577","retrieved":1656560520139,"image":"http://image.genie.co.kr/Y/IMAGE/IMG_ALBUM/082/792/577/82792577_1656405942142_1_200x200.JPG"},{"title":"DDKD","contents":"허성현 (Huh)","link":"http://mw.genie.co.kr/detail/albumInfo?axnm=82788606","retrieved":1656494220513,"image":"http://image.genie.co.kr/Y/IMAGE/IMG_ALBUM/082/788/606/82788606_1656468662619_1_200x200.JPG"},{"title":"열이올라요 (Heart Burn)","contents":"선미","link":"http://mw.genie.co.kr/detail/albumInfo?axnm=82792428","retrieved":1656494220518,"image":"http://image.genie.co.kr/Y/IMAGE/IMG_ALBUM/082/792/428/82792428_1656476805492_1_200x200.JPG"},{"title":"우리는 우리를","contents":"스웨덴세탁소","link":"http://mw.genie.co.kr/detail/albumInfo?axnm=82792142","retrieved":1656494220518,"image":"http://image.genie.co.kr/Y/IMAGE/IMG_ALBUM/082/792/142/82792142_1656410266542_1_200x200.JPG"},{"title":"키스 식스 센스 OST Part 9","contents":"김도희","link":"http://mw.genie.co.kr/detail/albumInfo?axnm=82789577","retrieved":1656494220518,"image":"http://image.genie.co.kr/Y/IMAGE/IMG_ALBUM/082/789/577/82789577_1656386884170_1_200x200.JPG"},{"title":"혼잣말이 많아졌어 (Cause You) (Prod. by 강타 (KANGTA)) - SM STATION","contents":"영준 &amp; 이예준","link":"http://mw.genie.co.kr/detail/albumInfo?axnm=82791693","retrieved":1656494220522,"image":"http://image.genie.co.kr/Y/IMAGE/IMG_ALBUM/082/791/693/82791693_1656479295539_1_200x200.JPG"},{"title":"사랑은 유사과학","contents":"Mudd the student","link":"http://mw.genie.co.kr/detail/albumInfo?axnm=82779379","retrieved":1656494220522,"image":"http://image.genie.co.kr/Y/IMAGE/IMG_ALBUM/082/779/379/82779379_1655916938678_1_200x200.JPG"},{"title":"실수로라도","contents":"왁스 (Wax)","link":"http://mw.genie.co.kr/detail/albumInfo?axnm=82792035","retrieved":1656494220525,"image":"http://image.genie.co.kr/Y/IMAGE/IMG_ALBUM/082/792/035/82792035_1656392432042_1_200x200.JPG"},{"title":"모래","contents":"우효","link":"http://mw.genie.co.kr/detail/albumInfo?axnm=82782917","retrieved":1656494220528,"image":"http://image.genie.co.kr/Y/IMAGE/IMG_ALBUM/082/782/917/82782917_1656380013858_1_200x200.JPG"},{"title":"MONO","contents":"빌리어코스티","link":"http://mw.genie.co.kr/detail/albumInfo?axnm=82789348","retrieved":1656494220532,"image":"http://image.genie.co.kr/Y/IMAGE/IMG_ALBUM/082/789/348/82789348_1656490389133_1_200x200.JPG"}]}